webhist/__init__.py
webhist/index.py
webhist/parser/__init__.py
webhist/parser/html_parser.py
webhist/parser/maff_parser.py
webhist/parser/parser.py
webhist-1.0.0.dist-info/COPYING
webhist-1.0.0.dist-info/COPYING.LESSER
webhist-1.0.0.dist-info/METADATA
webhist-1.0.0.dist-info/WHEEL
webhist-1.0.0.dist-info/top_level.txt
webhist-1.0.0.dist-info/RECORD
