Metadata-Version: 2.1
Name: webhist
Version: 1.0.0
Summary: Saved webpage index and search
Home-page: https://github.com/projreality/webhist
Author: Samuel Li
Author-email: sli@projreality.com
License: https://www.gnu.org/licenses/lgpl.html
Platform: UNKNOWN
Requires-Dist: bs4
Requires-Dist: python-dateutil
Requires-Dist: maflib
Requires-Dist: tld
Requires-Dist: whoosh
